static_sitemaps/__init__.py
static_sitemaps/conf.py
static_sitemaps/generator.py
static_sitemaps/tasks.py
static_sitemaps/urls.py
static_sitemaps/util.py
static_sitemaps/views.py
static_sitemaps/management/__init__.py
static_sitemaps/management/commands/__init__.py
static_sitemaps/management/commands/refresh_sitemap.py
static_sitemaps/templates/static_sitemaps/sitemap_index.xml
django_sitemap_generator-4.6.0.dist-info/METADATA
django_sitemap_generator-4.6.0.dist-info/WHEEL
django_sitemap_generator-4.6.0.dist-info/top_level.txt
django_sitemap_generator-4.6.0.dist-info/RECORD
