Metadata-Version: 2.1
Name: django-sitemap-generator
Version: 4.6.0
Summary: Tool for generating sitemaps as static files
Home-page: https://github.com/Venus713/django-sitemap-generator
Author: venus713
Author-email: userstar713@gmail.com
License: UNKNOWN
Platform: UNKNOWN
Classifier: Development Status :: 4 - Beta
Classifier: Intended Audience :: Developers
Classifier: License :: OSI Approved :: MIT License
Classifier: Framework :: Django
Classifier: Programming Language :: Python :: 2.5
Classifier: Programming Language :: Python :: 2.6
Classifier: Programming Language :: Python :: 2.7
Classifier: Programming Language :: Python :: 3.4
Classifier: Programming Language :: Python :: 3.5
Classifier: Operating System :: POSIX
Classifier: Operating System :: POSIX :: Linux
Classifier: Topic :: Internet :: WWW/HTTP :: Dynamic Content
Classifier: Topic :: Software Development :: Libraries :: Python Modules
Requires-Dist: setuptools (>=0.6b1)
Requires-Dist: six (>=1.11.0)
Requires-Dist: Django (>=1.8)
